{
  "applicants": [
    {
      "firstName": "a",
      "middleName": "a",
      "lastName": "a",
      "sex": "Male",
      "phoneNumber": "1",
      "telNumber": "1",
      "faxNumber": "1",
      "email": "r@r",
      "placeBirth": "r",
      "dateBirth": "2022-01-01",
      "citizenship": "r",
      "civilStatus": "Single",
      "employer": "r",
      "empAddress": "r",
      "permanentAddress": "r",
      "presentOccupation": "r",
      "scholarship": "Yes",
      "scholarshipYes": "r",
      "goingStudy": "Full time",
      "reAdmission": "Yes",
      "areaSpecialization": "r",
      "listProfessor": [
        {
          "Prof": "r"
        },
        {
          "Prof": "w"
        },
        {
          "Prof": "e"
        }
      ],
      "semester": "First Semester",
      "semesterDate": "2023-2024",
      "tRecommend": "r",
      "nameRecommendation": "r",
      "addressRecommendation": "r",
      "futurePlans": "r",
      "instituitions": "r",
      "majorAcadbackgroud": "r",
      "degreeAcadbackgroud": "r",
      "dateAcadbackground": "2022-01-01",
      "appliedBefore": "Yes",
      "beforeYes": "r",
      "dateAppliedbefore": "2022-01-01",
      "nameLocemp": "r",
      "positionRecentemployer": "r",
      "dateRecentemployer": "2022-01-01",
      "dateRecentemployer2": "2022-01-01",
      "listHonor": "r",
      "publication": "r",
      "unpublishResearch": "r",
      "typeApplication": "International",
      "emailReco": "r",
      "tRecommend2": "r",
      "nameRecommendation2": "r",
      "addressRecommendation2": "r",
      "emailReco2": "r",
      "tRecommend3": "r",
      "nameRecommendation3": "r",
      "addressRecommendation3": "r",
      "emailReco3": "r",
      "programs": "Phd of Philosophy in Food Science",
      "Status": "Probationary",
      "Condition": "dsdadsasdasdasd sdsad skdkd dasdan dasdkdnkasdask dsa daskdad",
      "gpmcRemarks": "Accepted but with condition",
      "tempAdviser": "1",
      "id": 1
    },
    {
      "adminRemarks": "aa",
      "screening": "Endorse to GPMC",
      "id": 2
    },
    {
      "adminRemarks": "aa",
      "screening": "Endorse to GPMC",
      "id": 3
    },
    {
      "Status": "Decline",
      "Condition": "",
      "gpmcRemarks": "",
      "tempAdviser": "",
      "selectedAdviser": "",
      "selectedInstitute": "",
      "id": 4
    },
    {
      "screening": "Endorse to GPMC",
      "id": 5
    },
    {
      "screening": "Endorse to GPMC",
      "id": 6
    },
    {
      "Status": "Probationary",
      "Condition": "z",
      "gpmcRemarks": "zz",
      "tempAdviser": "",
      "selectedAdviser": "April Shayne L. Sulabo",
      "selectedInstitute": 1,
      "id": 7
    },
    {
      "Status": "Probationary",
      "Condition": "dsdadsasdasdasd sdsad skdkd dasdan dasdkdnkasdask dsa daskdad",
      "gpmcRemarks": "Accepted but with condition",
      "tempAdviser": "1",
      "id": 8
    },
    {
      "Status": "Regular",
      "Condition": "dsdadsasdasdasd sdsad skdkd dasdan dasdkdnkasdask dsa daskdad",
      "gpmcRemarks": "Accepted but with condition",
      "tempAdviser": "1",
      "id": 9
    },
    {
      "firstName": "",
      "middleName": "",
      "lastName": "",
      "sex": "",
      "phoneNumber": "",
      "telNumber": "",
      "faxNumber": "",
      "email": "",
      "placeBirth": "",
      "dateBirth": "",
      "citizenship": "",
      "civilStatus": "",
      "employer": "",
      "empAddress": "",
      "permanentAddress": "",
      "presentOccupation": "",
      "scholarship": "",
      "scholarshipYes": "",
      "goingStudy": "",
      "reAdmission": "",
      "areaSpecialization": "",
      "listProfessor": "1asssa",
      "semester": "",
      "semesterDate": "",
      "tRecommend": "",
      "nameRecommendation": "",
      "addressRecommendation": "",
      "futurePlans": "",
      "instituitions": "",
      "majorAcadbackgroud": "",
      "degreeAcadbackgroud": "",
      "dateAcadbackground": "",
      "appliedBefore": "",
      "beforeYes": "",
      "dateAppliedbefore": "",
      "nameLocemp": "",
      "positionRecentemployer": "",
      "dateRecentemployer": "",
      "dateRecentemployer2": "",
      "listHonor": "",
      "publication": "",
      "unpublishResearch": "",
      "typeApplication": "",
      "emailReco": "",
      "tRecommend2": "",
      "nameRecommendation2": "",
      "addressRecommendation2": "",
      "emailReco2": "",
      "tRecommend3": "",
      "nameRecommendation3": "",
      "addressRecommendation3": "",
      "emailReco3": "",
      "programs": "",
      "id": 10
    },
    {
      "firstName": "rrrrr",
      "id": 11
    },
    {
      "adminRemarks": "dd",
      "screening": "Endorse to GPMC",
      "id": 12
    },
    {
      "firstName": "a",
      "middleName": "",
      "lastName": "",
      "sex": "",
      "phoneNumber": "",
      "telNumber": "",
      "faxNumber": "",
      "email": "",
      "placeBirth": "",
      "dateBirth": "",
      "citizenship": "",
      "civilStatus": "",
      "employer": "",
      "empAddress": "",
      "permanentAddress": "",
      "presentOccupation": "",
      "scholarship": "",
      "scholarshipYes": "",
      "goingStudy": "",
      "reAdmission": "",
      "areaSpecialization": "",
      "listProfessor": "",
      "semester": "",
      "semesterDate": "",
      "tRecommend": "",
      "nameRecommendation": "",
      "addressRecommendation": "",
      "futurePlans": "",
      "instituitions": "",
      "majorAcadbackgroud": "",
      "degreeAcadbackgroud": "",
      "dateAcadbackground": "",
      "appliedBefore": "",
      "beforeYes": "",
      "dateAppliedbefore": "",
      "nameLocemp": "",
      "positionRecentemployer": "",
      "dateRecentemployer": "",
      "dateRecentemployer2": "",
      "listHonor": "",
      "publication": "",
      "unpublishResearch": "",
      "typeApplication": "",
      "emailReco": "",
      "tRecommend2": "",
      "nameRecommendation2": "",
      "addressRecommendation2": "",
      "emailReco2": "",
      "tRecommend3": "",
      "nameRecommendation3": "",
      "addressRecommendation3": "",
      "emailReco3": "",
      "programs": "",
      "id": 13
    },
    {
      "firstName": "yeheyt",
      "middleName": "",
      "lastName": "",
      "sex": "",
      "phoneNumber": "",
      "telNumber": "",
      "faxNumber": "",
      "email": "",
      "placeBirth": "",
      "dateBirth": "",
      "citizenship": "",
      "civilStatus": "",
      "employer": "",
      "empAddress": "",
      "permanentAddress": "",
      "presentOccupation": "",
      "scholarship": "",
      "scholarshipYes": "",
      "goingStudy": "",
      "reAdmission": "",
      "areaSpecialization": "",
      "listProfessor": "",
      "semester": "",
      "semesterDate": "",
      "tRecommend": "",
      "nameRecommendation": "",
      "addressRecommendation": "",
      "futurePlans": "",
      "instituitions": "",
      "majorAcadbackgroud": "",
      "degreeAcadbackgroud": "",
      "dateAcadbackground": "",
      "appliedBefore": "",
      "beforeYes": "",
      "dateAppliedbefore": "",
      "nameLocemp": "",
      "positionRecentemployer": "",
      "dateRecentemployer": "",
      "dateRecentemployer2": "",
      "listHonor": "",
      "publication": "",
      "unpublishResearch": "",
      "typeApplication": "",
      "emailReco": "",
      "tRecommend2": "",
      "nameRecommendation2": "",
      "addressRecommendation2": "",
      "emailReco2": "",
      "tRecommend3": "",
      "nameRecommendation3": "",
      "addressRecommendation3": "",
      "emailReco3": "",
      "programs": "",
      "id": 14
    },
    {
      "firstName": "zzzz",
      "middleName": "",
      "lastName": "",
      "sex": "",
      "phoneNumber": "",
      "telNumber": "",
      "faxNumber": "",
      "email": "",
      "placeBirth": "",
      "dateBirth": "",
      "citizenship": "",
      "civilStatus": "",
      "employer": "",
      "empAddress": "",
      "permanentAddress": "",
      "presentOccupation": "",
      "scholarship": "",
      "scholarshipYes": "",
      "goingStudy": "",
      "reAdmission": "",
      "areaSpecialization": "",
      "listProfessor": "",
      "semester": "",
      "semesterDate": "",
      "tRecommend": "",
      "nameRecommendation": "",
      "addressRecommendation": "",
      "futurePlans": "",
      "instituitions": "",
      "majorAcadbackgroud": "",
      "degreeAcadbackgroud": "",
      "dateAcadbackground": "",
      "appliedBefore": "",
      "beforeYes": "",
      "dateAppliedbefore": "",
      "nameLocemp": "",
      "positionRecentemployer": "",
      "dateRecentemployer": "",
      "dateRecentemployer2": "",
      "listHonor": "",
      "publication": "",
      "unpublishResearch": "",
      "typeApplication": "",
      "emailReco": "",
      "tRecommend2": "",
      "nameRecommendation2": "",
      "addressRecommendation2": "",
      "emailReco2": "",
      "tRecommend3": "",
      "nameRecommendation3": "",
      "addressRecommendation3": "",
      "emailReco3": "",
      "programs": "",
      "id": 15
    },
    {
      "firstName": "gegege",
      "middleName": "",
      "lastName": "",
      "sex": "",
      "phoneNumber": "",
      "telNumber": "",
      "faxNumber": "",
      "email": "",
      "placeBirth": "",
      "dateBirth": "",
      "citizenship": "",
      "civilStatus": "",
      "employer": "",
      "empAddress": "",
      "permanentAddress": "",
      "presentOccupation": "",
      "scholarship": "",
      "scholarshipYes": "",
      "goingStudy": "",
      "reAdmission": "",
      "areaSpecialization": "",
      "listProfessor": "",
      "semester": "",
      "semesterDate": "",
      "tRecommend": "",
      "nameRecommendation": "",
      "addressRecommendation": "",
      "futurePlans": "",
      "instituitions": "",
      "majorAcadbackgroud": "",
      "degreeAcadbackgroud": "",
      "dateAcadbackground": "",
      "appliedBefore": "",
      "beforeYes": "",
      "dateAppliedbefore": "",
      "nameLocemp": "",
      "positionRecentemployer": "",
      "dateRecentemployer": "",
      "dateRecentemployer2": "",
      "listHonor": "",
      "publication": "",
      "unpublishResearch": "",
      "typeApplication": "",
      "emailReco": "",
      "tRecommend2": "",
      "nameRecommendation2": "",
      "addressRecommendation2": "",
      "emailReco2": "",
      "tRecommend3": "",
      "nameRecommendation3": "",
      "addressRecommendation3": "",
      "emailReco3": "",
      "programs": "",
      "id": 16
    },
    {
      "firstName": "zzzz",
      "middleName": "",
      "lastName": "",
      "sex": "",
      "phoneNumber": "",
      "telNumber": "",
      "faxNumber": "",
      "email": "",
      "placeBirth": "",
      "dateBirth": "",
      "citizenship": "",
      "civilStatus": "",
      "employer": "",
      "empAddress": "",
      "permanentAddress": "",
      "presentOccupation": "",
      "scholarship": "",
      "scholarshipYes": "",
      "goingStudy": "",
      "reAdmission": "",
      "areaSpecialization": "",
      "listProfessor": "",
      "semester": "",
      "semesterDate": "",
      "tRecommend": "",
      "nameRecommendation": "",
      "addressRecommendation": "",
      "futurePlans": "",
      "instituitions": "",
      "majorAcadbackgroud": "",
      "degreeAcadbackgroud": "",
      "dateAcadbackground": "",
      "appliedBefore": "",
      "beforeYes": "",
      "dateAppliedbefore": "",
      "nameLocemp": "",
      "positionRecentemployer": "",
      "dateRecentemployer": "",
      "dateRecentemployer2": "",
      "listHonor": "",
      "publication": "",
      "unpublishResearch": "",
      "typeApplication": "",
      "emailReco": "",
      "tRecommend2": "",
      "nameRecommendation2": "",
      "addressRecommendation2": "",
      "emailReco2": "",
      "tRecommend3": "",
      "nameRecommendation3": "",
      "addressRecommendation3": "",
      "emailReco3": "",
      "programs": "",
      "id": 17
    },
    {
      "id": 18
    },
    {
      "id": 19
    },
    {
      "id": 20
    },
    {
      "id": 21
    },
    {
      "id": 22
    },
    {
      "id": 23
    },
    {
      "id": 24
    },
    {
      "id": 25
    },
    {
      "id": 26
    },
    {
      "id": 27
    },
    {
      "id": 28
    },
    {
      "id": 29
    },
    {
      "id": 30
    },
    {
      "id": 31
    },
    {
      "id": 32
    },
    {
      "id": 33
    },
    {
      "id": 34
    },
    {
      "id": 35
    },
    {
      "id": 36
    },
    {
      "id": 37
    },
    {
      "id": 38
    },
    {
      "firstName": "aaa",
      "middleName": "",
      "lastName": "aaa",
      "sex": "",
      "phoneNumber": "",
      "telNumber": "",
      "faxNumber": "",
      "email": "",
      "placeBirth": "",
      "dateBirth": "",
      "citizenship": "",
      "civilStatus": "",
      "employer": "",
      "empAddress": "",
      "permanentAddress": "",
      "presentOccupation": "",
      "scholarship": "",
      "scholarshipYes": "",
      "goingStudy": "",
      "reAdmission": "",
      "areaSpecialization": "",
      "listProfessor": "",
      "semester": "",
      "semesterDate": "",
      "tRecommend": "",
      "nameRecommendation": "",
      "addressRecommendation": "",
      "futurePlans": "",
      "instituitions": "",
      "majorAcadbackgroud": "",
      "degreeAcadbackgroud": "",
      "dateAcadbackground": "",
      "appliedBefore": "",
      "beforeYes": "",
      "dateAppliedbefore": "",
      "nameLocemp": "",
      "positionRecentemployer": "",
      "dateRecentemployer": "",
      "dateRecentemployer2": "",
      "listHonor": "",
      "publication": "",
      "unpublishResearch": "",
      "typeApplication": "",
      "emailReco": "",
      "tRecommend2": "",
      "nameRecommendation2": "",
      "addressRecommendation2": "",
      "emailReco2": "",
      "tRecommend3": "",
      "nameRecommendation3": "",
      "addressRecommendation3": "",
      "emailReco3": "",
      "programs": "",
      "id": 39
    },
    {
      "firstName": "aa",
      "middleName": "aa",
      "lastName": "",
      "sex": "",
      "phoneNumber": "",
      "telNumber": "",
      "faxNumber": "",
      "email": "",
      "placeBirth": "",
      "dateBirth": "",
      "citizenship": "",
      "civilStatus": "",
      "employer": "",
      "empAddress": "",
      "permanentAddress": "",
      "presentOccupation": "",
      "scholarship": "",
      "scholarshipYes": "",
      "goingStudy": "",
      "reAdmission": "",
      "areaSpecialization": "",
      "listProfessor": "",
      "semester": "",
      "semesterDate": "",
      "tRecommend": "",
      "nameRecommendation": "",
      "addressRecommendation": "",
      "futurePlans": "",
      "instituitions": "",
      "majorAcadbackgroud": "",
      "degreeAcadbackgroud": "",
      "dateAcadbackground": "",
      "appliedBefore": "",
      "beforeYes": "",
      "dateAppliedbefore": "",
      "nameLocemp": "",
      "positionRecentemployer": "",
      "dateRecentemployer": "",
      "dateRecentemployer2": "",
      "listHonor": "",
      "publication": "",
      "unpublishResearch": "",
      "typeApplication": "",
      "emailReco": "",
      "tRecommend2": "",
      "nameRecommendation2": "",
      "addressRecommendation2": "",
      "emailReco2": "",
      "tRecommend3": "",
      "nameRecommendation3": "",
      "addressRecommendation3": "",
      "emailReco3": "",
      "programs": "",
      "id": 40
    },
    {
      "firstName": "ddddd",
      "middleName": "a",
      "lastName": "a",
      "sex": "Male",
      "phoneNumber": "1",
      "telNumber": "1",
      "faxNumber": "1",
      "email": "r@r",
      "placeBirth": "r",
      "dateBirth": "2022-01-01",
      "citizenship": "r",
      "civilStatus": "Single",
      "employer": "r",
      "empAddress": "r",
      "permanentAddress": "r",
      "presentOccupation": "r",
      "scholarship": "Yes",
      "scholarshipYes": "r",
      "goingStudy": "Full time",
      "reAdmission": "Yes",
      "areaSpecialization": "r",
      "listProfessor": [
        {
          "Prof": "r"
        },
        {
          "Prof": "w"
        },
        {
          "Prof": "e"
        }
      ],
      "semester": "First Semester",
      "semesterDate": "2023-2024",
      "tRecommend": "r",
      "nameRecommendation": "r",
      "addressRecommendation": "r",
      "futurePlans": "r",
      "instituitions": "r",
      "majorAcadbackgroud": "r",
      "degreeAcadbackgroud": "r",
      "dateAcadbackground": "2022-01-01",
      "appliedBefore": "Yes",
      "beforeYes": "r",
      "dateAppliedbefore": "2022-01-01",
      "nameLocemp": "r",
      "positionRecentemployer": "r",
      "dateRecentemployer": "2022-01-01",
      "dateRecentemployer2": "2022-01-01",
      "listHonor": "r",
      "publication": "r",
      "unpublishResearch": "r",
      "typeApplication": "International",
      "emailReco": "r",
      "tRecommend2": "r",
      "nameRecommendation2": "r",
      "addressRecommendation2": "r",
      "emailReco2": "r",
      "tRecommend3": "r",
      "nameRecommendation3": "r",
      "addressRecommendation3": "r",
      "emailReco3": "r",
      "programs": "Phd of Philosophy in Food Science",
      "id": 41
    }
  ]
}